parse_and_list_markdown_files.py
parse_and_list_markdown_files.sh
pymarkdown_minisite.py
setup.py
pymarkdown_minisite.egg-info/PKG-INFO
pymarkdown_minisite.egg-info/SOURCES.txt
pymarkdown_minisite.egg-info/dependency_links.txt
pymarkdown_minisite.egg-info/gpl.txt
pymarkdown_minisite.egg-info/top_level.txt