Metadata-Version: 1.1
Name: pymarkdown-minisite
Version: 0.2
Summary: ['Parse a list of markdown files to a website with index. ']
Home-page: http://freehg.org/u/ArneBab/pymarkdown_minisite
Author: Arne Babenhauserheide
Author-email: arne_bab@web.de
License: GNU GPL-3 or later
Keywords: babtools,markdown
Platform: any
Classifier: License :: OSI Approved :: GNU General Public License (GPL)
Classifier: Programming Language :: Python
Classifier: Operating System :: OS Independent
Classifier: Topic :: Software Development :: Libraries :: Python Modules
Classifier: Intended Audience :: Developers
Classifier: Intended Audience :: End Users/Desktop
Classifier: Environment :: Console
Classifier: Development Status :: 4 - Beta
Requires: markdown (>=2.0)
